hatch_odoo/__init__.py
hatch_odoo/build_hook.py
hatch_odoo/config.py
hatch_odoo/hooks.py
hatch_odoo/metadata_hook.py
hatch_odoo-1.0.2.dist-info/METADATA
hatch_odoo-1.0.2.dist-info/WHEEL
hatch_odoo-1.0.2.dist-info/entry_points.txt
hatch_odoo-1.0.2.dist-info/licenses/LICENSE.txt
hatch_odoo-1.0.2.dist-info/RECORD
