Metadata-Version: 2.3
Name: hatch-odoo
Version: 1.0.2
Summary: A Hatch plugin for Odoo projects.
Project-URL: Documentation, https://github.com/acsone/hatch-odoo#readme
Project-URL: Issues, https://github.com/acsone/hatch-odoo/issues
Project-URL: Source, https://github.com/acsone/hatch-odoo
Author-email: Stéphane Bidoul <stephane.bidoul@acsone.eu>
License-Expression: MIT
License-File: LICENSE.txt
Classifier: Development Status :: 5 - Production/Stable
Classifier: Framework :: Hatch
Classifier: Framework :: Odoo
Classifier: Programming Language :: Python
Classifier: Programming Language :: Python :: 3.7
Classifier: Programming Language :: Python :: 3.8
Classifier: Programming Language :: Python :: 3.9
Classifier: Programming Language :: Python :: 3.10
Classifier: Programming Language :: Python :: 3.11
Classifier: Programming Language :: Python :: 3.12
Requires-Python: >=3.7
Requires-Dist: hatchling!=1.19.0,>=1.4.1
Requires-Dist: manifestoo-core[metadata]>0.8
Requires-Dist: tomli; python_version < '3.11'
Provides-Extra: test
Requires-Dist: build; extra == 'test'
Requires-Dist: editables; extra == 'test'
Requires-Dist: importlib-metadata; (python_version < '3.8') and extra == 'test'
Requires-Dist: packaging; extra == 'test'
Requires-Dist: pytest; extra == 'test'
Requires-Dist: pytest-cov; extra == 'test'
